
{"data":
[
  {"check":"","id":"100137","title":"李欢","date":"财务部","ganwei":"-","opr":"1","person":"10000"},
  {"check":"","id":"100137","title":"李欢","date":"财务部","ganwei":"-","opr":"1","person":"10000"},
  {"check":"","id":"100137","title":"李欢","date":"财务部","ganwei":"-","opr":"1","person":"10000"},
  {"check":"","id":"100137","title":"李欢","date":"财务部","ganwei":"-","opr":"1","person":"10000"},
  {"check":"","id":"100137","title":"李欢","date":"财务部","ganwei":"-","opr":"1","person":"10000"},
  {"check":"","id":"100137","title":"李欢","date":"财务部","ganwei":"-","opr":"1","person":"10000"},
  {"check":"","id":"100137","title":"李欢","date":"财务部","ganwei":"-","opr":"1","person":"10000"},
  {"check":"","id":"100137","title":"李欢","date":"财务部","ganwei":"-","opr":"1","person":"10000"},
  {"check":"","id":"100137","title":"李欢","date":"财务部","ganwei":"-","opr":"1","person":"10000"},
  {"check":"","id":"100137","title":"李欢","date":"财务部","ganwei":"-","opr":"1","person":"10000"},
  {"check":"","id":"100137","title":"李欢","date":"财务部","ganwei":"-","opr":"1","person":"10000"}
]}